flowa/__init__.py
flowa/_version.py
flowa/ai/__init__.py
flowa/ai/decisiontree.py
flowa/ai/imagemodel.py
flowa/ai/labelencoder.py
flowa/datasets/__init__.py
flowa/network/__init__.py
flowa/network/activations.py
flowa/types/__init__.py
flowa/utils/__init__.py
flowa-10.5.5.dist-info/LICENSE
flowa-10.5.5.dist-info/METADATA
flowa-10.5.5.dist-info/WHEEL
flowa-10.5.5.dist-info/top_level.txt
flowa-10.5.5.dist-info/RECORD
