Metadata-Version: 2.1
Name: flowa
Version: 10.5.5
Summary: flowa - Machine Learning Toolkit
Home-page: https://github.com/flowa-ai/flowa
Author: flowa (Discord: @flo.a)
Author-email: "flowa (Discord: @flo.a)" <flowa.dev@gmail.com>
License: MIT License
Project-URL: Github, https://github.com/flowa-ai
Project-URL: Repository, https://github.com/flowa-ai/
Project-URL: PyPi, https://pypi.org/project/flowa/
Keywords: flowa
Classifier: License :: OSI Approved :: MIT License
Classifier: Development Status :: 5 - Production/Stable
Classifier: Development Status :: 4 - Beta
Classifier: Development Status :: 3 - Alpha
Classifier: Development Status :: 2 - Pre-Alpha
Classifier: Development Status :: 1 - Planning
Classifier: Intended Audience :: Developers
Classifier: Intended Audience :: Science/Research
Classifier: License :: OSI Approved :: MIT License
Classifier: Programming Language :: Python
Classifier: Topic :: Software Development :: Libraries
Classifier: Topic :: Software Development :: Libraries :: Python Modules
Classifier: Topic :: Scientific/Engineering
Classifier: Topic :: Scientific/Engineering :: Artificial Intelligence
Classifier: Topic :: Scientific/Engineering :: Mathematics
Classifier: Typing :: Typed
Requires-Python: >=3.7
License-File: LICENSE
Requires-Dist: numpy
Requires-Dist: pandas
Requires-Dist: pathlib
